fid/__init__.py
fid/fid.py
fid_cli-0.3.4.dist-info/licenses/LICENSE
fid_cli-0.3.4.dist-info/METADATA
fid_cli-0.3.4.dist-info/WHEEL
fid_cli-0.3.4.dist-info/entry_points.txt
fid_cli-0.3.4.dist-info/top_level.txt
fid_cli-0.3.4.dist-info/RECORD
